uncertainty_wizard/__init__.py
uncertainty_wizard/internal_utils/__init__.py
uncertainty_wizard/internal_utils/_uwiz_warning.py
uncertainty_wizard/internal_utils/tf_version_resolver.py
uncertainty_wizard/models/__init__.py
uncertainty_wizard/models/_load_model.py
uncertainty_wizard/models/_uwiz_model.py
uncertainty_wizard/models/_stochastic/__init__.py
uncertainty_wizard/models/_stochastic/_abstract_stochastic.py
uncertainty_wizard/models/_stochastic/_from_keras.py
uncertainty_wizard/models/_stochastic/_functional_stochastic.py
uncertainty_wizard/models/_stochastic/_sequential_stochastic.py
uncertainty_wizard/models/_stochastic/_stochastic_mode.py
uncertainty_wizard/models/ensemble_utils/__init__.py
uncertainty_wizard/models/ensemble_utils/_callables.py
uncertainty_wizard/models/ensemble_utils/_lazy_contexts.py
uncertainty_wizard/models/ensemble_utils/_lazy_ensemble.py
uncertainty_wizard/models/ensemble_utils/_save_config.py
uncertainty_wizard/models/stochastic_utils/__init__.py
uncertainty_wizard/models/stochastic_utils/broadcaster.py
uncertainty_wizard/models/stochastic_utils/layers.py
uncertainty_wizard/quantifiers/__init__.py
uncertainty_wizard/quantifiers/mean_softmax.py
uncertainty_wizard/quantifiers/mutual_information.py
uncertainty_wizard/quantifiers/one_shot_classifiers.py
uncertainty_wizard/quantifiers/predictive_entropy.py
uncertainty_wizard/quantifiers/quantifier.py
uncertainty_wizard/quantifiers/quantifier_registry.py
uncertainty_wizard/quantifiers/regression_quantifiers.py
uncertainty_wizard/quantifiers/variation_ratio.py
uncertainty_wizard-0.4.0.dist-info/LICENSE
uncertainty_wizard-0.4.0.dist-info/METADATA
uncertainty_wizard-0.4.0.dist-info/WHEEL
uncertainty_wizard-0.4.0.dist-info/top_level.txt
uncertainty_wizard-0.4.0.dist-info/RECORD
