Metadata-Version: 2.1
Name: uncertainty-wizard
Version: 0.4.0
Summary: Quick access to uncertainty and confidence of Keras networks.
Home-page: https://github.com/testingautomated-usi/uncertainty_wizard
Author: Michael Weiss
Author-email: code@mweiss.ch
Classifier: Development Status :: 4 - Beta
Classifier: Programming Language :: Python :: 3
Classifier: Topic :: Scientific/Engineering :: Artificial Intelligence
Classifier: License :: OSI Approved :: MIT License
Classifier: Operating System :: OS Independent
Requires-Python: >=3.6
License-File: LICENSE
